[
    {
        "DATE": "2024-12-02 10:49:35",
        "NAME": "фывфыв",
        "CONTACT": "фвфывы",
        "TITLE": "1. Обслуживание 1с",
        "DESCRIPTION": "фывфыв",
        "FILES": []
    },
    {
        "DATE": "2024-12-02 16:51:02",
        "NAME": "фывфыв",
        "CONTACT": "фывфыв",
        "TITLE": "1. Обслуживание 1с",
        "DESCRIPTION": "фывфывфыв",
        "FILES": []
    },
    {
        "DATE": "2024-12-02 16:53:22",
        "NAME": "test",
        "CONTACT": "test",
        "TITLE": "1. Обслуживание 1с",
        "DESCRIPTION": "test",
        "FILES": []
    },
    {
        "DATE": "2024-12-03 13:25:19",
        "NAME": "Баишев Валерий Геннадьевич",
        "CONTACT": "89142916789",
        "TITLE": "1. Обслуживание 1с",
        "DESCRIPTION": "В кладке инструменты есть обработка \"Групповая обработка товаров\" есть возможно добавить в эту обработку функцию добавить товар из Документа?",
        "FILES": []
    },
    {
        "DATE": "2024-12-10 09:06:21",
        "NAME": "Бондаренко Р.С.",
        "CONTACT": "yhk-it@yandex.ru",
        "TITLE": "1. Обслуживание 1с",
        "DESCRIPTION": "В.Бестяхе проблема с выемкой после правки бухгалтера.",
        "FILES": []
    },
    {
        "DATE": "2025-01-09 15:59:59",
        "NAME": "Бондаренко Р.С.",
        "CONTACT": "yhk-it@yandex.ru",
        "TITLE": "1. Обслуживание 1с",
        "DESCRIPTION": "От бухгалтера:\r\nН.Б. по 20,12,2024 отчет закрыт идеален. Отчет по 25.12 не смогла закрыть 03,01,2025 т к мешал закрещ. эквайринг от 14,11,2024-ЯХБТ-000477 Федотов Дьулустан Егорович. Из-за чего я не понимаю. Все было закрыто по 20,12,2024г. сейчас я поправила ( сделала проведенным эквайринг ЯХБТ-000477 Федотов Дьулустан Егорович, т к чек пробит). Но 29,12,2024 они думая что пробили наличку на СЫРДАХСКОЕ ООО делают возврат, хотя по Z-ке никаких движений нет, и в отчете который они предоставили, поступлений нет и в ОФД нет, есть по ним (СЫРДАХСКОЕ ООО) только эквайринг, который есть в офд. Сегодня вылезет всяко в ошибку.",
        "FILES": []
    },
    {
        "DATE": "2025-01-13 14:36:14",
        "NAME": "Ольга Филипповна Овчаренко",
        "CONTACT": "формирование КУДИР с 2025 года (УСН Доходы минус Расходы) ",
        "TITLE": "1. Обслуживание 1с",
        "DESCRIPTION": "связаться по номеру 89644150784 ",
        "FILES": []
    },
    {
        "DATE": "2025-01-17 16:11:47",
        "NAME": "София",
        "CONTACT": "89681542454",
        "TITLE": "1. Обслуживание 1с",
        "DESCRIPTION": "Не выходит 5% НДС в чеке, надо вручную выводить ",
        "FILES": []
    },
    {
        "DATE": "2025-01-24 12:54:52",
        "NAME": "Гуслякова Татьяна Владимировна",
        "CONTACT": "89241665285",
        "TITLE": "1. Обслуживание 1с",
        "DESCRIPTION": "Добрый день.    Скажите как нам настроить выгрузку с  нашей 1с  в 1С бухгалтерию ( аутсорсинга).   Так как для сдачи отчётов теперь мы должны им  выгрузить  счёт -фактуры (  покупок ) .\r\n\r\n",
        "FILES": []
    },
    {
        "DATE": "2025-01-27 14:03:34",
        "NAME": "ИП Березовская Екатерина Викторовнп",
        "CONTACT": "89241722046",
        "TITLE": "1. Обслуживание 1с",
        "DESCRIPTION": "Закрыть доступ для кассиров в 2х магазинах, просматривать продажи друг друга.",
        "FILES": []
    },
    {
        "DATE": "2025-01-29 12:23:22",
        "NAME": "Иванова Сардана Семеновна",
        "CONTACT": "+79644160213",
        "TITLE": "1. Обслуживание 1с",
        "DESCRIPTION": "Добавить в базы Бухгалтерия и Управление торговлей новые ставки НДС",
        "FILES": []
    },
    {
        "DATE": "2025-02-04 13:46:14",
        "NAME": "Сабирова Татьяна Сергеевна",
        "CONTACT": "89244612346",
        "TITLE": "Охрана труда",
        "DESCRIPTION": "на официальном сайте ЯХК нужна вкладка для предоставления сводных данных о результатах проведения специальной оценки условий труда...\r\nможно предложить название вкладки..",
        "FILES": []
    },
    {
        "DATE": "2025-02-11 11:18:44",
        "NAME": "Головинская Людмила  Юрьевна",
        "CONTACT": "79142875149",
        "TITLE": "1. Обслуживание 1с",
        "DESCRIPTION": "Добрый день. М-н  Загадка.\r\nНет выемки за 10\/02\r\nСделайте  пжта\r\n",
        "FILES": []
    },
    {
        "DATE": "2025-02-11 11:18:45",
        "NAME": "Головинская Людмила  Юрьевна",
        "CONTACT": "79142875149",
        "TITLE": "1. Обслуживание 1с",
        "DESCRIPTION": "Добрый день. М-н  Загадка.\r\nНет выемки за 10\/02\r\nСделайте  пжта\r\n",
        "FILES": []
    },
    {
        "DATE": "2025-02-11 11:44:46",
        "NAME": "Головинская Людмила  Юрьевна",
        "CONTACT": "79142875149",
        "TITLE": "1. Обслуживание 1с",
        "DESCRIPTION": "Добрый день. М-н  Загадка.\r\nНет выемки за 10\/02\r\nСделайте  пжта\r\n",
        "FILES": []
    },
    {
        "DATE": "2025-02-11 16:08:31",
        "NAME": "Людмила",
        "CONTACT": "79142875149",
        "TITLE": "1. Обслуживание 1с",
        "DESCRIPTION": "Сделайте выемку пжта, срочно. Загадка , Автодорожная 40 , ЯХК ",
        "FILES": []
    },
    {
        "DATE": "2025-02-20 09:53:54",
        "NAME": "Будимир",
        "CONTACT": "89644189958",
        "TITLE": "1. Обслуживание 1с",
        "DESCRIPTION": "Изменить Поисковик УТ СИН. Сделать как у ИВН",
        "FILES": []
    },
    {
        "DATE": "2025-02-20 10:13:08",
        "NAME": "Будимир",
        "CONTACT": "89644189958",
        "TITLE": "1. Обслуживание 1с",
        "DESCRIPTION": "Изменить Поисковик УТ СИН. Сделать как у ИВН",
        "FILES": []
    },
    {
        "DATE": "2025-02-20 10:13:09",
        "NAME": "Будимир",
        "CONTACT": "89644189958",
        "TITLE": "1. Обслуживание 1с",
        "DESCRIPTION": "Изменить Поисковик УТ СИН. Сделать как у ИВН",
        "FILES": []
    },
    {
        "DATE": "2025-02-26 14:50:03",
        "NAME": "Белов Данил Вячеславович",
        "CONTACT": "+89243680221",
        "TITLE": "1. Обслуживание 1с",
        "DESCRIPTION": "Карточка БП000004844 Сахар Рафинад на остатках магазина Лена имеется с характеристикой и без. Сахар без характеристики невозможно оприходовать или же сделать с ним перестортицу. ",
        "FILES": []
    },
    {
        "DATE": "2025-03-03 07:57:20",
        "NAME": "Белов Данил Вячеславович",
        "CONTACT": "+89243680221",
        "TITLE": "1. Обслуживание 1с",
        "DESCRIPTION": "Оставлял заявку 26.02. на изменение характеристики БП000004844. Поставили 09.10.2023, 109,81, 157, из-за чего остаток увеличился на 25 рублей, надо изменить на 05.08.2022, 123,36, 162",
        "FILES": []
    },
    {
        "DATE": "2025-03-06 11:53:13",
        "NAME": "Бондаренко Р.С.",
        "CONTACT": "yhk-it@yandex.ru",
        "TITLE": "1. Обслуживание 1с",
        "DESCRIPTION": "В магазине \"Пчёлка\" слетели остатки.",
        "FILES": []
    },
    {
        "DATE": "2025-03-19 10:36:47",
        "NAME": "Ольга Николаевна",
        "CONTACT": "agrozoo20576@mail.ru",
        "TITLE": "1. Обслуживание 1с",
        "DESCRIPTION": "Переход из УТ 10.3 в УТ 11",
        "FILES": []
    },
    {
        "DATE": "2025-04-04 17:39:37",
        "NAME": "Людмила ",
        "CONTACT": "89841051057",
        "TITLE": "1. Обслуживание 1с",
        "DESCRIPTION": "Нужна консультация специалиста по учету. Конкретно имеются вопросы по ОСВ \r\nКод 763171",
        "FILES": []
    },
    {
        "DATE": "2025-04-04 17:42:39",
        "NAME": "Людмила ",
        "CONTACT": "89841051057",
        "TITLE": "1. Обслуживание 1с",
        "DESCRIPTION": "Здравствуйте! Нужна удаленная консультация специалиста по учету. Имеются вопросы по ОСВ. \r\nВаш клиент.: Код 763171",
        "FILES": []
    },
    {
        "DATE": "2025-04-04 17:43:23",
        "NAME": "Людмила ",
        "CONTACT": "89841051057",
        "TITLE": "3. Бухобслуживание 1С",
        "DESCRIPTION": "Здравствуйте! Нужна удаленная консультация специалиста по учету. Имеются вопросы по ОСВ. \r\nВаш клиент.: Код 763171",
        "FILES": []
    },
    {
        "DATE": "2025-04-22 12:55:59",
        "NAME": "Першаков Даниил Владимирович",
        "CONTACT": "+79995642610",
        "TITLE": "2. Обслуживание кассы",
        "DESCRIPTION": "Кассир, в магазине ЯХК, Нижний Бестях, неверно рассчитала суммы, пробитие чеков также прошло неверно (много), и натворила много нехорошего, плюс с ОФД не сходятся данные.\r\n\r\nVNC подключение: 192.168.26.211 - основной\r\nдоп: 192.168.1.228, 192.162.26.211\r\n\r\nКассир - телефон: 89241672411\r\nКассир - WhatsApp: +79142648392\r\n\r\nПроблема со слов Кассира: \r\n\"Наша проблема 16 числа контрагенту Новгородову Дм. Василь. по ошибке продавца была пробита вместо 10шт , 110шт хлеба бездрожжевого\r\nони приехали 18 числа. и сделали возврат 100шт бездрожж на сумму 8698рб\r\nчерез терминал возврат была сделана, а вот через ккм чек не вышло.\r\nконторагенты которые с договорами пробиваются в товароведе поэтому не смогла вытащить чек из ккм, куда надо было зайти\r\nи вот вижу в товароведе-продажи где возврат товаров от покупателей 2 чека возвратов проведенных стоят\"\r\n\r\n*P.S. Для связи со мной можете написать в Telegram\\WhatsApp по номеру указанному в заявке. Даниил (сист.администратор, ВРИО руководителя отдела ИТ и ИБ)",
        "FILES": []
    },
    {
        "DATE": "2025-05-12 15:44:46",
        "NAME": "Белов Данил Вячеславович",
        "CONTACT": "+89243680221",
        "TITLE": "1. Обслуживание 1с",
        "DESCRIPTION": "У магазина Юнимолл весят остатки на открытие магазина 17.04.25. только у них в программе, у нас остаток на начало 0 руб, как и должно быть. У магазина Фантазия не идет оценка розничного склада с товарным отчетом с 17на 18 марта 21 руб",
        "FILES": []
    },
    {
        "DATE": "2025-05-12 15:53:22",
        "NAME": "Белов Данил Вячеславович",
        "CONTACT": "+89243680221",
        "TITLE": "1. Обслуживание 1с",
        "DESCRIPTION": "У магазина Юнимолл весят остатки на открытие магазина 17.04.25. только у них в программе, у нас остаток на начало 0 руб, как и должно быть. У магазина Фантазия не идет оценка розничного склада с товарным отчетом с 17на 18 марта 21 руб",
        "FILES": []
    },
    {
        "DATE": "2025-05-16 16:42:23",
        "NAME": "Бондаренко Р.С.",
        "CONTACT": "+79294660047",
        "TITLE": "1. Обслуживание 1с",
        "DESCRIPTION": "В магазин \"Нива\" с синхронизацией не попадают новые цены. Сама синхнонизация центральной базы с УТ и магазинами работает.\r\n\r\nТоваровед магазина: +7 914 222 3198\r\nНач.торгового отдела: +7 996 914 6804",
        "FILES": []
    },
    {
        "DATE": "2025-05-19 16:15:02",
        "NAME": "Плешаков Александр Николаевич",
        "CONTACT": "89142813027",
        "TITLE": "1. Обслуживание 1с",
        "DESCRIPTION": "нужно подключить (программно) интегрированный терминал эквайринга к 1с далион автобизнес",
        "FILES": []
    },
    {
        "DATE": "2025-05-19 16:15:12",
        "NAME": "Плешаков Александр Николаевич",
        "CONTACT": "89142813027",
        "TITLE": "1. Обслуживание 1с",
        "DESCRIPTION": "нужно подключить (программно) интегрированный терминал эквайринга к 1с далион автобизнес",
        "FILES": []
    },
    {
        "DATE": "2025-06-06 09:09:23",
        "NAME": "Белов Данил Вячеславович",
        "CONTACT": "+89243680221",
        "TITLE": "1. Обслуживание 1с",
        "DESCRIPTION": "Якутский хлебокомбинат, м-н №4 не идет оценка склада с товарным отчетом с 7.02.25 на 425 рублей. У м-н Нива 12.07.24 есть установка цены в товарном отчете, которой нет в основной программе",
        "FILES": []
    },
    {
        "DATE": "2025-06-09 14:53:12",
        "NAME": "Данилюк О.Г.",
        "CONTACT": "89141750875",
        "TITLE": "1. Обслуживание 1с",
        "DESCRIPTION": "Со слов бухгалтера: за 30.05 и 4.06 не все ТТН с обменом попали в базу бухгалтерии.\r\n",
        "FILES": []
    },
    {
        "DATE": "2025-06-11 15:12:31",
        "NAME": "АВП",
        "CONTACT": "89241715511",
        "TITLE": "1. Обслуживание 1с",
        "DESCRIPTION": "тест",
        "FILES": []
    },
    {
        "DATE": "2025-06-27 12:35:39",
        "NAME": "АВП",
        "CONTACT": "89241715511",
        "TITLE": "1. Обслуживание 1с",
        "DESCRIPTION": "ТЕСТ",
        "FILES": []
    },
    {
        "DATE": "2025-07-30 10:52:55",
        "NAME": "Бондаренко Р.С.",
        "CONTACT": "+79294660047",
        "TITLE": "1. Обслуживание 1с",
        "DESCRIPTION": "В магазине \"Фантазия\" проблема с выемками. Нет за 28 и 29 июля.",
        "FILES": []
    },
    {
        "DATE": "2025-07-30 11:04:34",
        "NAME": "Бондаренко Р.С.",
        "CONTACT": "+79294660047",
        "TITLE": "1. Обслуживание 1с",
        "DESCRIPTION": "В магазине \"Фантазия\" проблема с выемками. Нет за 28 и 29 июля.",
        "FILES": []
    },
    {
        "DATE": "2025-07-31 15:23:02",
        "NAME": "Сивцева Елена",
        "CONTACT": "89142771065",
        "TITLE": "1. Обслуживание 1с",
        "DESCRIPTION": "После обновления программы 1 С , перестал работать сканер штрих кола",
        "FILES": []
    },
    {
        "DATE": "2025-08-19 16:35:21",
        "NAME": "Сардана",
        "CONTACT": "+7-964-416-02-13",
        "TITLE": "4. Системное администрирование",
        "DESCRIPTION": "Здравствуйте! Это ООО \"Релиенс\". У нас компьютер каждый раз сам по себе выключается через несколько минут после включения. Просим провести диагностику. Адрес офиса: ул. Орджоникидзе, д. 46\/2, офис 105.",
        "FILES": []
    },
    {
        "DATE": "2025-08-25 09:50:05",
        "NAME": "Белов Данил Вячеславович",
        "CONTACT": "+89243680221",
        "TITLE": "1. Обслуживание 1с",
        "DESCRIPTION": "У магазина Загадка не идут продажи и выемка с 17 числа на 144 рубля, сама выемка перестала автоматически формироваться. Якутский хлебокомбинат",
        "FILES": []
    },
    {
        "DATE": "2025-08-26 12:24:26",
        "NAME": "Василий",
        "CONTACT": "89241715511",
        "TITLE": "1. Обслуживание 1с",
        "DESCRIPTION": "`12 Ntcn",
        "FILES": []
    },
    {
        "DATE": "2025-08-26 12:38:24",
        "NAME": "Ирина",
        "CONTACT": "89142882777",
        "TITLE": "1. Обслуживание 1с",
        "DESCRIPTION": "проверка",
        "FILES": []
    },
    {
        "DATE": "2025-09-08 11:53:43",
        "NAME": "Тестовая новость",
        "CONTACT": "фывфыв",
        "TITLE": "1. Обслуживание 1с",
        "DESCRIPTION": "Nrcnsdsdadasd",
        "FILES": []
    },
    {
        "DATE": "2025-09-08 11:54:07",
        "NAME": "Тестовая новость",
        "CONTACT": "test",
        "TITLE": "1. Обслуживание 1с",
        "DESCRIPTION": "asdasdasdasdasd",
        "FILES": []
    },
    {
        "DATE": "2025-09-08 12:22:02",
        "NAME": "Тестовая новость",
        "CONTACT": "ТестовМаилРу",
        "TITLE": "1. Обслуживание 1с",
        "DESCRIPTION": "Test",
        "FILES": []
    },
    {
        "DATE": "2025-09-08 12:25:09",
        "NAME": "Тестовая новость",
        "CONTACT": "test",
        "TITLE": "1. Обслуживание 1с",
        "DESCRIPTION": "test",
        "FILES": []
    },
    {
        "DATE": "2025-09-08 12:26:56",
        "NAME": "Тестовая новость",
        "CONTACT": "test",
        "TITLE": "1. Обслуживание 1с",
        "DESCRIPTION": "asdasdas",
        "FILES": []
    },
    {
        "DATE": "2025-09-08 12:29:42",
        "NAME": "Тестовая новость",
        "CONTACT": "ТестовМаилРу",
        "TITLE": "1. Обслуживание 1с",
        "DESCRIPTION": "asdsadsadas",
        "FILES": []
    },
    {
        "DATE": "2025-09-09 08:45:24",
        "NAME": "Скрябин Михаил Михайлович",
        "CONTACT": "+79142320359",
        "TITLE": "1. Обслуживание 1с",
        "DESCRIPTION": "СВИТОПТ НДС 1 кв 2025 с комментарием - к сдаче 09.09.2025 анализ счета 68-02 и ОСВ 76-АВ и расшифровка авансовых счетов фактур не сходится по строке 070 декларации \r\n\r\nпри заполнении ошибку выдала которую ранее выправляли по сводной счет фактурам по рознице ",
        "FILES": []
    },
    {
        "DATE": "2025-09-09 11:22:42",
        "NAME": "Ольга Валентиновна ",
        "CONTACT": "89142214101",
        "TITLE": "Отчетность кадровая, перечисление зп",
        "DESCRIPTION": "Направление КП",
        "FILES": []
    },
    {
        "DATE": "2025-09-12 09:50:18",
        "NAME": "Александра ",
        "CONTACT": "89990600095",
        "TITLE": "1. Обслуживание 1с",
        "DESCRIPTION": "Здравствуйте, хотим перейти с Эвотора на 1с. Интересуют ваши услуги, условия",
        "FILES": []
    },
    {
        "DATE": "2025-09-12 10:12:06",
        "NAME": "Тестовая новость",
        "CONTACT": "test",
        "TITLE": "1. Обслуживание 1с",
        "DESCRIPTION": "asdasdasdasd",
        "FILES": []
    },
    {
        "DATE": "2025-09-12 10:12:54",
        "NAME": "Тестовая новость",
        "CONTACT": "test",
        "TITLE": "1. Обслуживание 1с",
        "DESCRIPTION": "asdasdasdasd",
        "FILES": []
    },
    {
        "DATE": "2025-09-12 10:13:40",
        "NAME": "Тестовая новость",
        "CONTACT": "test",
        "TITLE": "1. Обслуживание 1с",
        "DESCRIPTION": "asdasdasdasd",
        "FILES": []
    },
    {
        "DATE": "2025-09-12 16:07:12",
        "NAME": "Наталья",
        "CONTACT": "n.sergeeva@yakutsk.2gis.ru",
        "TITLE": "1. Обслуживание 1с",
        "DESCRIPTION": "Добрый день! сколько стоит обслуживание 1с бухгалтерия в год?\r\nсколько стоит пакет часов?\r\nсколько стоит подключение 1с-Отчетность?",
        "FILES": []
    },
    {
        "DATE": "2025-09-16 10:25:02",
        "NAME": "Скрябин Михаил Михайлович",
        "CONTACT": "+79142320359",
        "TITLE": "1. Обслуживание 1с",
        "DESCRIPTION": "Есть ли какая то обработка по выравниванию остатков по расчетам с поставщиками (счет 60) и с покупателями (счет 62)  например, на 1 сентября 2025 года между программами  Управлением торговлей и Бухгалтерия предприятия Чтобы ведомости расчетов в УТ совпадали с ОСВ по счету 60,62 по каждой фирме по отдельности ",
        "FILES": []
    },
    {
        "DATE": "2025-09-24 12:20:55",
        "NAME": "Сардана",
        "CONTACT": "+79644160213",
        "TITLE": "1. Обслуживание 1с",
        "DESCRIPTION": "Здравствуйте! Нужно обновить 1С Бухгалтерию и Управление торговлей на компьютере",
        "FILES": []
    },
    {
        "DATE": "2025-09-25 08:36:41",
        "NAME": "Скрябин Михаил Михайлович",
        "CONTACT": "+79142320359",
        "TITLE": "Декларация НДС и ОСВ сч 90 не сходится ",
        "DESCRIPTION": "Есть разница между декларацией по налогу на прибыль с 3 кв 24 года и НДС за 3 кв 24 года (НДС больше)  по СВИТ ГРУПП .Нашел корректировки реализации номер 5, 3, 6, 7 (сумма 7383,90 ндс 1084,15 без НДС +6299,75) подскажите как нужно декларацию по НДС исправить....видимо что-то вручную надо добавлять .. за 4 кв 24г разница еще больше Надо как-то исправлять и сдать корректирующие декларации",
        "FILES": []
    },
    {
        "DATE": "2025-09-30 07:33:52",
        "NAME": "Скрябин Михаил Михайлович",
        "CONTACT": "+79142320359",
        "TITLE": "1. Обслуживание 1с",
        "DESCRIPTION": "Доброе утро с УТ выгрузку проверьте все ли документы выгружены в бухгалтерию? СЛТК например не вижу в бухгалтерии",
        "FILES": []
    },
    {
        "DATE": "2025-09-30 09:27:52",
        "NAME": "Бучельников Артур Николаевич",
        "CONTACT": "mku_cb2021@mail.ru",
        "TITLE": "Обращение как к партнёру Касперского",
        "DESCRIPTION": "Здравствуйте!Вы указаны в партнёрах Касперского.\r\nМы,МКУ \"ЦБ МР \"Ленский район\" РС(Я) ИНН 1414017804\r\nс начала 2026 года хотели бы пользоваться ПО Касперского,а именно Kaspersky Endpoint Security для бизнеса Стандартный .На скрине указан продукт пробную версию которого мы скачали и он нас устраивает.По видимому нам нужно будет от 60 до 90 лицензий(пока уточняется).Подскажите пожалуйста есть ли возможность подключения такого количества лицензий к данному продукту?Как будет происходить процесс покупки лицензий?Так как мы госучреждение,то не можем просто купить и оплатить лицензии,всё строится на договоре и оплате по счёту.Каким образом наш контрактный управляющий может связаться с Вашим отделом продаж или менеджером отвечающим за такие вопросы?Спасибо за внимание!\r\n ",
        "FILES": []
    },
    {
        "DATE": "2025-10-05 11:04:51",
        "NAME": "Скрябин Михаил Михайлович",
        "CONTACT": "+79142320359",
        "TITLE": "1. Обслуживание 1с",
        "DESCRIPTION": "Здравствуйте \r\n\r\nесть фирма работает в САБИ (несколько фирм там) нужно одну из них оттуда настроить чтобы учет велся в 1С\r\nА также ищу у кого они ранее обслуживались \r\n\r\nпоходу локальная версия на каждую фирму отдельная 1с -база вход.\r\nООО Экофорс  ИНН 1435334890  \r\n \r\nили может на другую колмпанию зарегистрирована программа \r\n \r\nООО Транзит Сервис 1435047782\r\nООО Трэйдер 1435302369\r\nИп Гордеева НА  143512746532  есть есть интерес напишите ",
        "FILES": []
    },
    {
        "DATE": "2025-10-07 11:30:32",
        "NAME": "Скрябин Михаил Михайлович",
        "CONTACT": "+79142320359",
        "TITLE": "1. Обслуживание 1с",
        "DESCRIPTION": "ИП Турнин работает без НДС  в бухгалтерии по передачам товара между фирмами проводки как будто с НДС Внутри документа НДС не выделен. Проверите  ",
        "FILES": []
    },
    {
        "DATE": "2025-10-13 11:09:45",
        "NAME": "Тестовая новость",
        "CONTACT": "testas",
        "TITLE": "1. Обслуживание 1с",
        "DESCRIPTION": "asdasdas",
        "FILES": []
    },
    {
        "DATE": "2025-10-13 11:13:16",
        "NAME": "Тест",
        "CONTACT": "+79841182886",
        "TITLE": "4. Системное администрирование",
        "DESCRIPTION": "Почему Байбал говорит \"Влад квадрат\"?",
        "FILES": []
    },
    {
        "DATE": "2025-10-13 11:22:23",
        "NAME": "test",
        "CONTACT": "test",
        "TITLE": "1. Обслуживание 1с",
        "DESCRIPTION": "asdasdasd",
        "FILES": []
    },
    {
        "DATE": "2025-10-14 20:26:59",
        "NAME": "Михаил Скрябин",
        "CONTACT": "89142320359",
        "TITLE": "1. Обслуживание 1с",
        "DESCRIPTION": "Здравствуйте у вас такая обработка? Выявлять расхождения по расчетам с покупателями в программах УТ и Бухгалтерия на определенную дату? Хорошо б если еще в бухгалтерии создавать корректировки долга либо списание-уменьшение\/увеличение  задолженности по выявленным суммам и по договорам ",
        "FILES": []
    },
    {
        "DATE": "2025-10-17 11:54:17",
        "NAME": "Бондаренко Р.С.",
        "CONTACT": "yhk-it@yandex.ru",
        "TITLE": "1. Обслуживание 1с",
        "DESCRIPTION": "В магазине \"Фантазия\" что то с остатуками не так.\r\nСо слов продавца: обмен проходит, но остатки не меняются, несмотря на новые приходы.\r\n",
        "FILES": []
    },
    {
        "DATE": "2025-10-24 14:02:23",
        "NAME": "Скрябин Михаил Михайлович",
        "CONTACT": "+79142320359",
        "TITLE": "1. Обслуживание 1с",
        "DESCRIPTION": "ИП АНАХИНА в Управление торговлей как-то можно скорректировать остатки на 30.09.2025г чтобы не было красноты в обеих сторонах \r\n\r\nна конец 30.09.2025- 275 274,29 руб должно быть ",
        "FILES": []
    },
    {
        "DATE": "2025-11-01 10:48:46",
        "NAME": "Скрябин Михаил Михайлович",
        "CONTACT": "+79142320359",
        "TITLE": "1. Обслуживание 1с",
        "DESCRIPTION": "ИП Анахина можно подключить продление подписки-обещанный платеж.. вроде сегодня оплачивают ",
        "FILES": []
    },
    {
        "DATE": "2025-11-05 12:07:27",
        "NAME": "Скрябин Михаил Михайлович",
        "CONTACT": "+79142320359",
        "TITLE": "1. Обслуживание 1с",
        "DESCRIPTION": "По ИП Анахина и СВИТОПТ обнаружил в бухгалтерии не проведенные документы по кассе в основном за 24 год  Можете выяснить причину? при закрытии месяца они почему не провелись ? ",
        "FILES": []
    },
    {
        "DATE": "2025-11-07 10:09:56",
        "NAME": "Скрябин Михаил Михайлович",
        "CONTACT": "+79142320359",
        "TITLE": "1. Обслуживание 1с",
        "DESCRIPTION": "Здравствуйте прошу помочь в этом вопросе : Свит Опт НДС-5%, но по возвратам товара бывают суммы НДС к вычету и налоговая запрашивает каждый раз подтверждающие документы по квартально. Пришло требование по 3кв. 25 года на сумму 13341 руб. расшифровку строки направляю.. и там почему то ставить ставку 20\/120ставку хотя в самом документе стоит 5%  Можно их вообще не показывать в декларации не заявлять к вычету.. много времени занимает подготовка ответа.. не подскажете как ? ",
        "FILES": []
    },
    {
        "DATE": "2025-11-11 14:47:12",
        "NAME": "Белов Данил Вячеславович",
        "CONTACT": "+89243680221",
        "TITLE": "1. Обслуживание 1с",
        "DESCRIPTION": "Якутский хлебокомбинат у магазина Юнимолл за 6.10.25 не идет отчет о розничных продажах с z-отчетом на 572 рубля. По z-отчету 113 чеков, в программе их только 111.",
        "FILES": []
    },
    {
        "DATE": "2025-11-15 06:40:14",
        "NAME": "Скрябин Михаил Михайлович",
        "CONTACT": "+79142320359",
        "TITLE": "1. Обслуживание 1с",
        "DESCRIPTION": "ИП Анахина СВИТ ОПТ СВИТГРУПП и ИП Турнин \r\n\r\nнет электронных адресов клиентов в бухгалтерии \r\nВ торговле есть в бухгалтерии нет \r\n\r\nПример клиент АСПЕКТ ООО эл адрес в торговле прописан",
        "FILES": []
    },
    {
        "DATE": "2025-11-15 06:40:36",
        "NAME": "Скрябин Михаил Михайлович",
        "CONTACT": "+79142320359",
        "TITLE": "1. Обслуживание 1с",
        "DESCRIPTION": "ИП Анахина СВИТ ОПТ СВИТГРУПП и ИП Турнин \r\n\r\nнет электронных адресов клиентов в бухгалтерии \r\nВ торговле есть в бухгалтерии нет \r\n\r\nПример клиент АСПЕКТ ООО эл адрес в торговле прописан",
        "FILES": []
    },
    {
        "DATE": "2025-11-17 09:01:44",
        "NAME": "Рубанов Павел Юрьевич",
        "CONTACT": "+79244618015",
        "TITLE": "1. Обслуживание 1с",
        "DESCRIPTION": "Имеются проблемы с автоматический обменом в магазина ЯХК \"Нижний Бестях\/Колосок\/Лена\/Фантазия\". Возможно имеются  проблемы и в других магазинах(для уточнения этого нужно мониторить более продолжительное время)",
        "FILES": []
    },
    {
        "DATE": "2025-12-01 10:43:30",
        "NAME": "Рубанов Павел Юрьевич",
        "CONTACT": "+79244618015",
        "TITLE": "1. Обслуживание 1с",
        "DESCRIPTION": "Якутский хлебокомбинат. В магазине \"Лена\" нужно поправить выемку",
        "FILES": []
    },
    {
        "DATE": "2025-12-02 01:18:44",
        "NAME": "POaiMgGrydEXLuEML",
        "CONTACT": "kukebuke25@gmail.com",
        "TITLE": "1. Обслуживание 1с",
        "DESCRIPTION": "iDBqIqNRandOecdUtY",
        "FILES": []
    },
    {
        "DATE": "2025-12-02 01:18:49",
        "NAME": "POaiMgGrydEXLuEML",
        "CONTACT": "kukebuke25@gmail.com",
        "TITLE": "1. Обслуживание 1с",
        "DESCRIPTION": "iDBqIqNRandOecdUtY",
        "FILES": []
    },
    {
        "DATE": "2025-12-02 01:18:54",
        "NAME": "POaiMgGrydEXLuEML",
        "CONTACT": "kukebuke25@gmail.com",
        "TITLE": "1. Обслуживание 1с",
        "DESCRIPTION": "iDBqIqNRandOecdUtY",
        "FILES": []
    },
    {
        "DATE": "2025-12-03 17:23:33",
        "NAME": "Сидоров Матвей",
        "CONTACT": "89841178529",
        "TITLE": "1. Обслуживание 1с",
        "DESCRIPTION": "Здравствуйте\r\nПосле перехода на фреш слетел сертификат ИП одной организации (Сидоров Степан). Самой флешки с сертификатом не нашли. Тогда что делаем? ЭДО и реглам. отчеты тп при запуске требует вставки его ЭЦП.\r\n\r\nПишет \"Укажите носитель для открытия контейнера SCARD\\rutoken_lt_468465a2\\0A00\\AFA2\"",
        "FILES": []
    },
    {
        "DATE": "2025-12-03 17:23:38",
        "NAME": "Сидоров Матвей",
        "CONTACT": "89841178529",
        "TITLE": "1. Обслуживание 1с",
        "DESCRIPTION": "Здравствуйте\r\nПосле перехода на фреш слетел сертификат ИП одной организации (Сидоров Степан). Самой флешки с сертификатом не нашли. Тогда что делаем? ЭДО и реглам. отчеты тп при запуске требует вставки его ЭЦП.\r\n\r\nПишет \"Укажите носитель для открытия контейнера SCARD\\rutoken_lt_468465a2\\0A00\\AFA2\"",
        "FILES": []
    },
    {
        "DATE": "2025-12-05 12:42:49",
        "NAME": "Скрябин Михаил Михайлович",
        "CONTACT": "+79142320359",
        "TITLE": "1. Обслуживание 1с",
        "DESCRIPTION": "Здравствуйте  Проверьте подключение к сервису 1С. Отчетность Свитгрупп 1400027545\r\nЛК по ЕНС дает информацию на ноябрь при обновлении выдает следующие шаги\r\n\r\nЗаявление на подключение от 07.11.2025 статус Одобрено \r\nМожет надо было ЭЦП директора или как \r\n\r\nИП Анахина и СвитОпт нет ошибок",
        "FILES": []
    },
    {
        "DATE": "2025-12-08 21:42:27",
        "NAME": "anSMjGTMzdCGzPbFt",
        "CONTACT": "kutuyeze002@gmail.com",
        "TITLE": "1. Обслуживание 1с",
        "DESCRIPTION": "LToAdLLThOwblvmcYU",
        "FILES": []
    },
    {
        "DATE": "2025-12-08 21:42:32",
        "NAME": "anSMjGTMzdCGzPbFt",
        "CONTACT": "kutuyeze002@gmail.com",
        "TITLE": "1. Обслуживание 1с",
        "DESCRIPTION": "LToAdLLThOwblvmcYU",
        "FILES": []
    },
    {
        "DATE": "2025-12-08 21:42:37",
        "NAME": "anSMjGTMzdCGzPbFt",
        "CONTACT": "kutuyeze002@gmail.com",
        "TITLE": "1. Обслуживание 1с",
        "DESCRIPTION": "LToAdLLThOwblvmcYU",
        "FILES": []
    },
    {
        "DATE": "2025-12-16 09:27:08",
        "NAME": "Скрябин Михаил Михайлович",
        "CONTACT": "+79142320359",
        "TITLE": "1. Обслуживание 1с",
        "DESCRIPTION": "Сервис 1С Отчетность активация нужна СВИТГРУПП 1400027545  \r\nвчера оплатили ",
        "FILES": []
    },
    {
        "DATE": "2025-12-16 09:42:05",
        "NAME": "Рубанов Павел Юрьевич",
        "CONTACT": "+79244618015",
        "TITLE": "1. Обслуживание 1с",
        "DESCRIPTION": "Проблемы с обменов у магазинов ЯХК",
        "FILES": []
    },
    {
        "DATE": "2025-12-16 12:10:47",
        "NAME": "Скрябин Михаил Михайлович",
        "CONTACT": "+79142320359",
        "TITLE": "1. Обслуживание 1с",
        "DESCRIPTION": "Трудовая книжка по ИП Анахина  ЕФС выдает такую ошибку - Ошибка чтения XML-документа: Ошибка проверки по XSD схеме. Строка 1, колонка 1660. Недопустимо пустое значение, значение должно быть не меньше допустимой minLength «1» для «ТипНепустаяСтрока». (код ошибки: 07010421)\r\n\r\nстатус принято в обработке и восклицательный знак\r\n\r\nотчет ЕФС от 16.12.25 не отправляет при этом. Отправка не может быть начата Дождитесь  завершения предыдущей операции",
        "FILES": []
    },
    {
        "DATE": "2025-12-16 14:39:51",
        "NAME": "Рубанов Павел Юрьевич",
        "CONTACT": "+79244618015",
        "TITLE": "1. Обслуживание 1с",
        "DESCRIPTION": "В магазине ЯХК \"Прометей\" выручка \"не идет\" с основной базой",
        "FILES": []
    }
]